{
  "url": "https://www.metmuseum.org/about-the-met",
  "timestamp": "2025-08-19T10:18:15.171016",
  "extracted": {
    "results": [
      {
        "url": "https://www.metmuseum.org/about-the-met",
        "raw_content": "## \n\n![About The Met]()\n\n# About The Met\n\nThe Met presents over 5,000 years of art from around the world for everyone to experience and enjoy.\n\n## About the Museum\n\nThe Metropolitan Museum of Art presents over 5,000 years of art from around the world for everyone to experience and enjoy. The Museum lives in two iconic sites in New York City\u2014[The Met Fifth Avenue](https://www.metmuseum.org/plan-your-visit/met-fifth-avenue)\u00a0and [The Met Cloisters](https://www.metmuseum.org/plan-your-visit/met-cloisters). Millions of people also take part in The Met experience online.\n\nSince its founding in 1870, The Met has always aspired to be more than a treasury of rare and beautiful objects. Every day, art comes alive in the Museum's galleries and through its exhibitions and events, revealing new ideas and unexpected connections across time and across cultures.\n\n### Mission Statement\n\nThe Metropolitan Museum of Art collects, studies, conserves, and presents significant works of art across time and cultures in order to connect all people to creativity, knowledge, ideas, and one another.\n\n## About the Museum\n\nThe Metropolitan Museum of Art presents over 5,000 years of art from around the world for everyone to experience and enjoy. The Museum lives in two iconic sites in New York City\u2014[The Met Fifth Avenue](https://www.metmuseum.org/plan-your-visit/met-fifth-avenue)\u00a0and [The Met Cloisters](https://www.metmuseum.org/plan-your-visit/met-cloisters). Millions of people also take part in The Met experience online.\n\nSince its founding in 1870, The Met has always aspired to be more than a treasury of rare and beautiful objects. Every day, art comes alive in the Museum's galleries and through its exhibitions and events, revealing new ideas and unexpected connections across time and across cultures.\n\n### Mission Statement\n\nThe Metropolitan Museum of Art collects, studies, conserves, and presents significant works of art across time and cultures in order to connect all people to creativity, knowledge, ideas, and one another.\n\n## \n\n![Archival image of installing Assyrian reliefs in the Ancient Near East wing]()\n\n### [History of the Museum](/about-the-met/history)\n\n![A view of the Neoclassical fa\u00e7ade of The Met Fifth Avenue]()\n\n### [Leadership](/about-the-met/leadership)\n\n## \n\n![A woman and a young boy sitting together on a bench looking up at two Roman frescoes]()\n\n### [Collection areas](/about-the-met/collection-areas)\n\n![Conservator looking through a microscope at a Cezanne painting on a table with another Cezanne painting displayed on an easel in the background]()\n\n### [Conservation and research](/about-the-met/conservation-and-scientific-research)\n\n## \n\n![Two marble busts from ancient Greece on rectangular pedestals]()\n\n### [Policies and documents](/about-the-met/policies-and-documents)\n\n![A man crossing his arms, wearing a face mask looking at prints by Goya on display]()\n\n### [Contact information](/about-the-met/contact)\n\n![Man standing in Lehman court surrounded by plants]()\n\n### [Press](/press)\n\n## Get involved\n\n## \n\n![Volunteer gesturing to a portrait of a seated man in front of a crowd]()\n\n### [Volunteer](/join-and-give/volunteer)\n\n![A view of the Temple of Dendur at The Met Fifth Avenue with two statues of pharaohs on either side]()\n\n### [Support The Met](https://www.metmuseum.org/join-and-give/support)\n\n## \n\n![Two interns inspect a textile using magnifying glasses]()\n\n### [Career opportunities](https://metmuseum.wd5.myworkdayjobs.com/en-US/metmuseumcareers)\n\n![Two young men sketching in the galleries]()\n\n### [Internships](/about-the-met/internships)\n\n![Man looking through a microscope surrounded by screens]()\n\n### [The Met Fellowship Program](/about-the-met/fellowships)",
        "images": []
      }
    ],
    "failed_results": [],
    "response_time": 0.01,
    "request_id": "f3de1ece-aebd-45af-9666-874b6e8f026c"
  }
}