{
  "timestamp": "20250818_225642",
  "url": "https://www.nyc.gov/nyc-resources/categories.page",
  "response": {
    "results": [
      {
        "url": "https://www.nyc.gov/nyc-resources/categories.page",
        "raw_content": "NYC Resources | Categories | City of New York\n\n===============\n\n**Visiting NYC?**Find events, attractions, deals, and more at [**nyctourism.com**](https://www.nyctourism.com/)[](https://www.nyc.gov/nyc-resources/categories.page# \"close\")\n\n[Skip Main Navigation](https://www.nyc.gov/nyc-resources/categories.page#main)\n\nMenu\n\nThe Official Website of the City of New York\n\n[![Image 1: NYC.gov Home](https://www.nyc.gov/assets/home/images/global/nyc.png)](https://www.nyc.gov/)\n\n[Text Size](https://www.nyc.gov/home/text-size.page)\n\nPowered by [![Image 2: Google Translate](https://www.gstatic.com/images/branding/googlelogo/1x/googlelogo_color_42x16dp.png)Translate](https://translate.google.com/)\n\nSearch Search\n\nPrimary Navigation\n------------------\n\nThe official website of NYC\n---------------------------\n\n*   [Home](https://www.nyc.gov/)\n*   [NYC Resources](https://www.nyc.gov/nyc-resources/categories.page)\n*   [NYC311](https://portal.311.nyc.gov/)\n*   [Office of the Mayor](https://www.nyc.gov/office-of-the-mayor/index.page)\n*   [Events](https://www.nyc.gov/events/index.html)\n*   [Connect](https://www.nyc.gov/connect/newsletter-sign-up.page)\n*   [Jobs](https://www.nyc.gov/jobs/index.page)\n\nSearch \n\nSecondary Navigation\n--------------------\n\n[Categories](https://www.nyc.gov/nyc-resources/categories.page)[Agencies](https://www.nyc.gov/nyc-resources/agencies.page)[Programs](https://www.nyc.gov/nyc-resources/programs.page)\n\nDirectory of NYC resources organized by category\n================================================\n\n[Benefits & Support](https://portal.311.nyc.gov/kacategory/?id=311-121 \"Benefits & Support\")\n--------------------------------------------------------------------------------------------\n\n[Cash & Expenses](https://portal.311.nyc.gov/kacategory/?id=311-23)[Children & Families](https://portal.311.nyc.gov/kacategory/?id=311-25)[Food](https://portal.311.nyc.gov/kacategory/?id=311-22)[Health Insurance](https://portal.311.nyc.gov/kacategory/?id=311-24)[Homelessness](https://portal.311.nyc.gov/kacategory/?id=311-21)[Housing](https://portal.311.nyc.gov/kacategory/?id=311-20)[Immigrants](https://portal.311.nyc.gov/kacategory/?id=311-26)[LGBTQ](https://portal.311.nyc.gov/kacategory/?id=311-27)[Older Adults](https://portal.311.nyc.gov/kacategory/?id=311-29)[People with Disabilities](https://portal.311.nyc.gov/kacategory/?id=311-28)[Veterans & Military](https://portal.311.nyc.gov/kacategory/?id=311-30)[Volunteer & Donate](https://portal.311.nyc.gov/kacategory/?id=311-31)\n\n[**Benefits & Support Page**](https://portal.311.nyc.gov/kacategory/?id=311-121)\n\n* * *\n\n[Businesses & Consumers](https://portal.311.nyc.gov/kacategory/?id=311-2 \"Businesses & Consumers\")\n--------------------------------------------------------------------------------------------------\n\n[Businesses](https://portal.311.nyc.gov/kacategory/?id=311-32)[Consumers](https://portal.311.nyc.gov/kacategory/?id=311-33)[NYC Business Portal](https://portal.311.nyc.gov/kacategory/?id=311-1000)\n\n[**Businesses & Consumers Page**](https://portal.311.nyc.gov/kacategory/?id=311-2)\n\n* * *\n\n[Courts & Law](https://portal.311.nyc.gov/kacategory/?id=311-3 \"Courts & Law\")\n------------------------------------------------------------------------------\n\n[Courts & Law](https://portal.311.nyc.gov/kacategory/?id=311-35)[Jails & Incarcerated People](https://portal.311.nyc.gov/kacategory/?id=311-34)\n\n[**Courts & Law Page**](https://portal.311.nyc.gov/kacategory/?id=311-3)\n\n* * *\n\n[Culture & Recreation](https://portal.311.nyc.gov/kacategory/?id=311-4 \"Culture & Recreation\")\n----------------------------------------------------------------------------------------------\n\n[Arts & Culture](https://portal.311.nyc.gov/kacategory/?id=311-37)[Events](https://portal.311.nyc.gov/kacategory/?id=311-38)[New York City & Visitors](https://portal.311.nyc.gov/kacategory/?id=311-39)[Parks & Recreation](https://portal.311.nyc.gov/kacategory/?id=311-36)\n\n[**Culture & Recreation Page**](https://portal.311.nyc.gov/kacategory/?id=311-4)\n\n* * *\n\n[Education](https://portal.311.nyc.gov/kacategory/?id=311-5 \"Education\")\n------------------------------------------------------------------------\n\n[Adult Learning](https://portal.311.nyc.gov/kacategory/?id=311-44)[After School & Summer Programs](https://portal.311.nyc.gov/kacategory/?id=311-42)[College](https://portal.311.nyc.gov/kacategory/?id=311-43)[Early Childhood](https://portal.311.nyc.gov/kacategory/?id=311-40)[Pre-K to Grade 12](https://portal.311.nyc.gov/kacategory/?id=311-41)\n\n[**Education Page**](https://portal.311.nyc.gov/kacategory/?id=311-5)\n\n* * *\n\n[Employment](https://portal.311.nyc.gov/kacategory/?id=311-6 \"Employment\")\n--------------------------------------------------------------------------\n\n[Employees](https://portal.311.nyc.gov/kacategory/?id=311-46)[Jobs & Training](https://portal.311.nyc.gov/kacategory/?id=311-45)\n\n[**Employment Page**](https://portal.311.nyc.gov/kacategory/?id=311-6)\n\n* * *\n\n[Environment](https://portal.311.nyc.gov/kacategory/?id=311-7 \"Environment\")\n----------------------------------------------------------------------------\n\n[Air](https://portal.311.nyc.gov/kacategory/?id=311-48)[Environmental Protection](https://portal.311.nyc.gov/kacategory/?id=311-49)[Water](https://portal.311.nyc.gov/kacategory/?id=311-47)\n\n[**Environment Page**](https://portal.311.nyc.gov/kacategory/?id=311-7)\n\n* * *\n\n[Government & Elections](https://portal.311.nyc.gov/kacategory/?id=311-9 \"Government & Elections\")\n--------------------------------------------------------------------------------------------------\n\n[City Government](https://portal.311.nyc.gov/kacategory/?id=311-52)[Elections & Voting](https://portal.311.nyc.gov/kacategory/?id=311-53)[Foreign Government](https://portal.311.nyc.gov/kacategory/?id=311-54)\n\n[**Government & Elections Page**](https://portal.311.nyc.gov/kacategory/?id=311-9)\n\n* * *\n\n[Health](https://portal.311.nyc.gov/kacategory/?id=311-10 \"Health\")\n-------------------------------------------------------------------\n\n[Health Care](https://portal.311.nyc.gov/kacategory/?id=311-56)[Health Insurance](https://portal.311.nyc.gov/kacategory/?id=311-55)[Healthy Living](https://portal.311.nyc.gov/kacategory/?id=311-57)[Public Health](https://portal.311.nyc.gov/kacategory/?id=311-58)\n\n[**Health Page**](https://portal.311.nyc.gov/kacategory/?id=311-10)\n\n* * *\n\n[Housing & Buildings](https://portal.311.nyc.gov/kacategory/?id=311-11 \"Housing & Buildings\")\n---------------------------------------------------------------------------------------------\n\n[Builders & Contractors](https://portal.311.nyc.gov/kacategory/?id=311-63)[Buildings & Property](https://portal.311.nyc.gov/kacategory/?id=311-64)[Homeowners](https://portal.311.nyc.gov/kacategory/?id=311-62)[Housing Options](https://portal.311.nyc.gov/kacategory/?id=311-59)[Rental Property Owners](https://portal.311.nyc.gov/kacategory/?id=311-61)[Tenants](https://portal.311.nyc.gov/kacategory/?id=311-60)\n\n[**Housing & Buildings Page**](https://portal.311.nyc.gov/kacategory/?id=311-11)\n\n* * *\n\n[Noise](https://portal.311.nyc.gov/kacategory/?id=311-12 \"Noise\")\n-----------------------------------------------------------------\n\n[**Noise Page**](https://portal.311.nyc.gov/kacategory/?id=311-12)\n\n* * *\n\n[Pets, Pests & Wildlife](https://portal.311.nyc.gov/kacategory/?id=311-13 \"Pets, Pests & Wildlife\")\n---------------------------------------------------------------------------------------------------\n\n[Pests & Wildlife](https://portal.311.nyc.gov/kacategory/?id=311-67)[Pets](https://portal.311.nyc.gov/kacategory/?id=311-66)\n\n[**Pets, Pests & Wildlife Page**](https://portal.311.nyc.gov/kacategory/?id=311-13)\n\n* * *\n\n[Public Safety](https://portal.311.nyc.gov/kacategory/?id=311-14 \"Public Safety\")\n---------------------------------------------------------------------------------\n\n[Preparedness & Recovery](https://portal.311.nyc.gov/kacategory/?id=311-69)[Safety & Crime](https://portal.311.nyc.gov/kacategory/?id=311-68)\n\n[**Public Safety Page**](https://portal.311.nyc.gov/kacategory/?id=311-14)\n\n* * *\n\n[Records](https://portal.311.nyc.gov/kacategory/?id=311-15 \"Records\")\n---------------------------------------------------------------------\n\n[Birth & Adoption](https://portal.311.nyc.gov/kacategory/?id=311-71)[City Agencies](https://portal.311.nyc.gov/kacategory/?id=311-78)[Death](https://portal.311.nyc.gov/kacategory/?id=311-72)[Education](https://portal.311.nyc.gov/kacategory/?id=311-76)[Health](https://portal.311.nyc.gov/kacategory/?id=311-75)[ID & Citizenship](https://portal.311.nyc.gov/kacategory/?id=311-70)[Marriage & Partnership](https://portal.311.nyc.gov/kacategory/?id=311-73)[Property](https://portal.311.nyc.gov/kacategory/?id=311-74)[Public Safety](https://portal.311.nyc.gov/kacategory/?id=311-77)\n\n[**Records Page**](https://portal.311.nyc.gov/kacategory/?id=311-15)\n\n* * *\n\n[Sidewalks, Streets & Highways](https://portal.311.nyc.gov/kacategory/?id=311-16 \"Sidewalks, Streets & Highways\")\n-----------------------------------------------------------------------------------------------------------------\n\n[Bridges & Tunnels](https://portal.311.nyc.gov/kacategory/?id=311-79)[Sidewalks](https://portal.311.nyc.gov/kacategory/?id=311-80)[Streets & Highways](https://portal.311.nyc.gov/kacategory/?id=311-81)\n\n[**Sidewalks, Streets & Highways Page**](https://portal.311.nyc.gov/kacategory/?id=311-16)\n\n* * *\n\n[Taxes](https://portal.311.nyc.gov/kacategory/?id=311-17 \"Taxes\")\n-----------------------------------------------------------------\n\n[Business](https://portal.311.nyc.gov/kacategory/?id=311-83)[Fraud](https://portal.311.nyc.gov/kacategory/?id=311-87)[Income](https://portal.311.nyc.gov/kacategory/?id=311-84)[Preparation](https://portal.311.nyc.gov/kacategory/?id=311-82)[Property](https://portal.311.nyc.gov/kacategory/?id=311-85)[Sales](https://portal.311.nyc.gov/kacategory/?id=311-86)\n\n[**Taxes Page**](https://portal.311.nyc.gov/kacategory/?id=311-17)\n\n* * *\n\n[Transportation](https://portal.311.nyc.gov/kacategory/?id=311-18 \"Transportation\")\n-----------------------------------------------------------------------------------\n\n[Accessible Transportation](https://portal.311.nyc.gov/kacategory/?id=311-93)[Bikes](https://portal.311.nyc.gov/kacategory/?id=311-92)[Boats & Airplanes](https://portal.311.nyc.gov/kacategory/?id=311-91)[Driving, Parking & Tickets](https://portal.311.nyc.gov/kacategory/?id=311-88)[Public Transportation](https://portal.311.nyc.gov/kacategory/?id=311-89)[Taxis & Car Services](https://portal.311.nyc.gov/kacategory/?id=311-90)\n\n[**Transportation Page**](https://portal.311.nyc.gov/kacategory/?id=311-18)\n\n* * *\n\n[Trash & Recycling](https://portal.311.nyc.gov/kacategory/?id=311-8 \"Trash & Recycling\")\n----------------------------------------------------------------------------------------\n\n[Cleaning](https://portal.311.nyc.gov/kacategory/?id=311-51)[Collection & Disposal](https://portal.311.nyc.gov/kacategory/?id=311-50)\n\n[**Trash & Recycling Page**](https://portal.311.nyc.gov/kacategory/?id=311-8)\n\nNYC.gov footer\n\nMore on NYC.gov\n---------------\n\n*   [Directory of City Agencies](https://www.nyc.gov/nyc-resources/agencies.page)\n*   [Contact NYC Government](https://www.nyc.gov/home/contact-us.page)\n*   [City Employees](https://a127-ess.nyc.gov/)\n*   [Notify NYC](https://a858-nycnotify.nyc.gov/notifynyc/)\n*   [City Store](https://a856-citystore.nyc.gov/)\n*   [Stay Connected](https://www.nyc.gov/connect/social-media.page)\n*   [NYC Mobile Apps](https://www.nyc.gov/connect/applications.page)\n*   [Maps](https://www.nyc.gov/nyc-resources/nyc-maps.page)\n*   [Residents Toolkit](https://www.nyc.gov/nyc-resources/resident-toolkit.page)\n\nNYC.gov in Other Languages\n--------------------------\n\n*   [\u0627\u0644\u0639\u0631\u0628\u064a\u0629](javascript:setLanguage('ar'))\n*   [\u09ac\u09be\u0999\u09be\u09b2\u09bf](javascript:setLanguage('bn'))\n*   [\u4e2d\u6587](javascript:setLanguage('zh-CN'))\n*   [Krey\u00f2l Ayisyen](javascript:setLanguage('ht'))\n*   [Polskie](javascript:setLanguage('pl'))\n*   [Espa\u00f1ol](javascript:setLanguage('es'))\n*   [\u0420\u0443\u0441\u0441\u043a\u0438\u0439](javascript:setLanguage('ru'))\n*   [Fran\u00e7ais](javascript:setLanguage('fr'))\n*   [\ud55c\uad6d\uc5b4](javascript:setLanguage('ko'))\n*   [\u0627\u064f\u0631\u062f\u064f\u0648](javascript:setLanguage('ur'))\n*   [English](javascript:setLanguage('en'))\n\n[![Image 3: NYC Logo](https://www.nyc.gov/assets/home/images/global/nyc_white@x2.png)](http://www.nyc.gov/)\n\n\u00a9 City of New York. 2025 All Rights Reserved,\n\nNYC is a trademark and service mark of the City of New York.\n\n[Privacy Policy.](https://www.nyc.gov/home/privacy-policy.page)[Terms of Use.](https://www.nyc.gov/home/terms-of-use.page)[Learn more about NYC.gov Accessibility Commitment.](https://www.nyc.gov/nyc-resources/website-accessibility-statement.page)\n\n![Image 4](https://fonts.gstatic.com/s/i/productlogos/translate/v14/24px.svg)\n\nOriginal text\n\nRate this translation\n\nYour feedback will be used to help improve Google Translate\n",
        "images": []
      }
    ],
    "failed_results": [],
    "response_time": 0.01,
    "request_id": "601960d9-9644-463e-94c6-77c47c4b3911"
  },
  "cost": 0.01
}